{
  "name": "key:custom.supercuteskins.pack.name",
  "author": "4J Studios",
  "skins": [
    {
      "id": "woof",
      "name": "key:custom.supercuteskins.woof",
      "texture": "skins/woof.png",
      "model": "slim",
      "order": 1
    },
    {
      "id": "mew",
      "name": "key:custom.supercuteskins.mew",
      "texture": "skins/mew.png",
      "model": "slim",
      "order": 2
    },
    {
      "id": "cheep",
      "name": "key:custom.supercuteskins.cheep",
      "texture": "skins/cheep.png",
      "order": 3
    },
    {
      "id": "rawr",
      "name": "key:custom.supercuteskins.rawr",
      "texture": "skins/rawr.png",
      "order": 4
    },
    {
      "id": "whinny",
      "name": "key:custom.supercuteskins.whinny",
      "texture": "skins/whinny.png",
      "model": "slim",
      "order": 5
    },
    {
      "id": "spotty",
      "name": "key:custom.supercuteskins.spotty",
      "texture": "skins/spotty.png",
      "model": "slim",
      "order": 6
    },
    {
      "id": "sniff",
      "name": "key:custom.supercuteskins.sniff",
      "texture": "skins/sniff.png",
      "order": 7
    },
    {
      "id": "spit",
      "name": "key:custom.supercuteskins.spit",
      "texture": "skins/spit.png",
      "order": 8
    },
    {
      "id": "squirt",
      "name": "key:custom.supercuteskins.squirt",
      "texture": "skins/squirt.png",
      "order": 9
    },
    {
      "id": "patty",
      "name": "key:custom.supercuteskins.patty",
      "texture": "skins/patty.png",
      "model": "slim",
      "order": 10
    },
    {
      "id": "ringo",
      "name": "key:custom.supercuteskins.ringo",
      "texture": "skins/ringo.png",
      "order": 11
    },
    {
      "id": "scoop",
      "name": "key:custom.supercuteskins.scoop",
      "texture": "skins/scoop.png",
      "model": "slim",
      "order": 12
    },
    {
      "id": "pop",
      "name": "key:custom.supercuteskins.pop",
      "texture": "skins/pop.png",
      "order": 13
    },
    {
      "id": "beep",
      "name": "key:custom.supercuteskins.beep",
      "texture": "skins/beep.png",
      "order": 14
    },
    {
      "id": "root",
      "name": "key:custom.supercuteskins.root",
      "texture": "skins/root.png",
      "model": "slim",
      "order": 15
    }
  ]
}
