{
  "meta": {
    "displayName": "Banana Guard",
    "displayNameId": "IDS_SKINS_DLCSKIN00004448_DISPLAYNAME"
  },
  "offsets": {
    "head":         { "x": 0, "y": 1,  "z": 0 },
    "hat":          { "x": 0, "y": 1,  "z": 0 },
    "body":         { "x": 0, "y": 1,  "z": 0 },
    "right_arm":    { "x": 0, "y": 1,  "z": 0 },
    "left_arm":     { "x": 0, "y": 1, "z": 0 },
    "right_leg":    { "x": 0, "y": 0,  "z": 0 },
    "left_leg":     { "x": 0, "y": 0,  "z": 0 }
  },
  "armor_offsets": {
    "helmet": { "x": 0, "y": 2, "z": 0 },
    "chestplate": { "x": 0, "y": 2, "z": 0 },
    "leggings": { "x": 0, "y": 0, "z": 0 },
    "boots": { "x": 0, "y": 0, "z": 0 }
  },
  "hide": [ "jacket", "left_sleeve", "right_sleeve","left_pants", "right_pants", "legs"],
  "texture": {
    "width": 64,
    "height": 64
  },
  "bones": [
    {
      "name": "body_addon",
      "attach": "BODY",
      "cubes": [
        {
          "origin": [
            -4.0,
            0.0,
            -4.0
          ],
          "size": [
            4.0,
            6.0,
            2.0
          ],
          "uv": [
            24,
            0
          ],
          "inflate": 0.01,
          "mirror": false
        },
        {
          "origin": [
            -4.0,
            0.0,
            2.0
          ],
          "size": [
            4.0,
            6.0,
            2.0
          ],
          "uv": [
            56,
            0
          ],
          "inflate": 0.01,
          "mirror": false
        },
        {
          "origin": [
            0.0,
            0.0,
            -4.0
          ],
          "size": [
            4.0,
            6.0,
            2.0
          ],
          "uv": [
            24,
            0
          ],
          "inflate": 0.01,
          "mirror": false
        },
        {
          "origin": [
            0.0,
            0.0,
            2.0
          ],
          "size": [
            4.0,
            6.0,
            2.0
          ],
          "uv": [
            56,
            0
          ],
          "inflate": 0.01,
          "mirror": false
        },
        {
          "origin": [
            -4.0,
            6.0,
            -4.0
          ],
          "size": [
            4.0,
            6.0,
            2.0
          ],
          "uv": [
            0,
            32
          ],
          "inflate": 0.01,
          "mirror": false
        },
        {
          "origin": [
            -4.0,
            12.0,
            -4.0
          ],
          "size": [
            4.0,
            3.0,
            2.0
          ],
          "uv": [
            0,
            40
          ],
          "inflate": 0.01,
          "mirror": false
        },
        {
          "origin": [
            -4.0,
            6.0,
            2.0
          ],
          "size": [
            4.0,
            6.0,
            2.0
          ],
          "uv": [
            12,
            32
          ],
          "inflate": 0.01,
          "mirror": false
        },
        {
          "origin": [
            -4.0,
            12.0,
            2.0
          ],
          "size": [
            4.0,
            3.0,
            2.0
          ],
          "uv": [
            12,
            40
          ],
          "inflate": 0.01,
          "mirror": false
        },
        {
          "origin": [
            0.0,
            6.0,
            -4.0
          ],
          "size": [
            4.0,
            6.0,
            2.0
          ],
          "uv": [
            0,
            32
          ],
          "inflate": 0.01,
          "mirror": false
        },
        {
          "origin": [
            0.0,
            12.0,
            -4.0
          ],
          "size": [
            4.0,
            3.0,
            2.0
          ],
          "uv": [
            0,
            40
          ],
          "inflate": 0.01,
          "mirror": false
        },
        {
          "origin": [
            0.0,
            6.0,
            2.0
          ],
          "size": [
            4.0,
            6.0,
            2.0
          ],
          "uv": [
            12,
            32
          ],
          "inflate": 0.01,
          "mirror": false
        },
        {
          "origin": [
            0.0,
            12.0,
            2.0
          ],
          "size": [
            4.0,
            3.0,
            2.0
          ],
          "uv": [
            12,
            40
          ],
          "inflate": 0.01,
          "mirror": false
        },
        {
          "origin": [
            0.0,
            12.0,
            -2.0
          ],
          "size": [
            4.0,
            3.0,
            4.0
          ],
          "uv": [
            0,
            57
          ],
          "inflate": 0.01,
          "mirror": false
        },
        {
          "origin": [
            -4.0,
            12.0,
            -2.0
          ],
          "size": [
            4.0,
            3.0,
            4.0
          ],
          "uv": [
            0,
            57
          ],
          "inflate": 0.01,
          "mirror": false
        }
      ]
    },
    {
      "name": "right_leg_addon",
      "attach": "RIGHT_LEG",
      "cubes": [
        {
          "origin": [
            -2.0,
            0.0,
            -2.0
          ],
          "size": [
            4.0,
            9.0,
            4.0
          ],
          "uv": [
            0,
            16
          ],
          "inflate": 0.01,
          "mirror": false
        }
      ]
    },
    {
      "name": "left_leg_addon",
      "attach": "LEFT_LEG",
      "cubes": [
        {
          "origin": [
            -2.0,
            0.0,
            -2.0
          ],
          "size": [
            4.0,
            9.0,
            4.0
          ],
          "uv": [
            16,
            48
          ],
          "inflate": 0.01,
          "mirror": false
        }
      ]
    }
  ]
}