{
  "meta": {
    "displayName": "Giant Panda",
    "displayNameId": "IDS_DLCSKIN00001006_DISPLAYNAME"
  },
  "texture": {
    "width": 64,
    "height": 64
  },
  "bones": [
    {
      "name": "head_addon",
      "attach": "HEAD",
      "cubes": [
        {
          "origin": [
            1.99,
            -10.0,
            0.0
          ],
          "size": [
            3.0,
            3.0,
            1.0
          ],
          "uv": [
            24,
            0
          ],
          "inflate": 0.01,
          "mirror": false
        },
        {
          "origin": [
            -4.99,
            -10.0,
            0.0
          ],
          "size": [
            3.0,
            3.0,
            1.0
          ],
          "uv": [
            24,
            0
          ],
          "inflate": 0.01,
          "mirror": false
        }
      ]
    },
    {
      "name": "body_addon",
      "attach": "BODY",
      "cubes": [
        {
          "origin": [
            -1.0,
            10.0,
            2.0
          ],
          "size": [
            2.0,
            2.0,
            2.0
          ],
          "uv": [
            56,
            0
          ],
          "inflate": 0.01,
          "mirror": false
        }
      ]
    }
  ]
}